DESCRIPTION.rst
MANIFEST.in
setup.py
ligament_sftp/__init__.py
ligament_sftp.egg-info/PKG-INFO
ligament_sftp.egg-info/SOURCES.txt
ligament_sftp.egg-info/dependency_links.txt
ligament_sftp.egg-info/requires.txt
ligament_sftp.egg-info/top_level.txt