Metadata-Version: 1.1
Name: ligament-sftp
Version: 0.0.4.dev
Summary: A set of sftp build tasks for ligament
Home-page: http://github.com/Adjective-Object/ligament_jinja
Author: Adjective-Object
Author-email: mhuan13@gmail.com
License: Apache 2
Keywords: ligament grunt build automation jinja
Platform: UNKNOWN
Classifier: Development Status :: 3 - Alpha
Classifier: Intended Audience :: Developers
Classifier: Topic :: Software Development :: Build Tools
Classifier: License :: OSI Approved :: Apache Software License
Classifier: Programming Language :: Python :: 2.7
